{
  "id": "grammar",
  "title": "Grammar",
  "questions": [
    {
      "points": 200,
      "question": "In grammar, this part of speech describes an action or state.",
      "answer": "What is a verb?"
    },
    {
      "points": 400,
      "question": "In grammar, this term refers to a word that modifies a noun.",
      "answer": "What is an adjective?"
    },
    {
      "points": 600,
      "question": "In the sentence \"They packed ____ bags for the trip,\" this possessive word correctly fills the blank.",
      "answer": "What is their?"
    },
    {
      "points": 800,
      "question": "These are words that sound the same but have different meanings.",
      "answer": "What are homophones?"
    },
    {
      "points": 1000,
      "question": "According to the source material, this is the rarest word in the dictionary.",
      "answer": "What is quizzaciously?"
    }
  ]
}
